{"2023": {"Free Cash Flow": "25742000.0", "Repurchase Of Capital Stock": "nan", "Repayment Of Debt": "-40250000.0", "Issuance Of Debt": "37098000.0", "Capital Expenditure": "-9100000.0", "Interest Paid Supplemental Data": "1234000.0", "Income Tax Paid Supplemental Data": "5250000.0", "End Cash Position": "24104000.0", "Beginning Cash Position": "4183000.0", "Changes In Cash": "19921000.0", "Financing Cash Flow": "-5821000.0", "Cash Flow From Continuing Financing Activities": "-5821000.0", "Net Other Financing Charges": "-2669000.0", "Net Common Stock Issuance": "nan", "Common Stock Payments": "nan", "Net Issuance Payments Of Debt": "-3152000.0", "Net Short Term Debt Issuance": "-1864000.0", "Short Term Debt Payments": "-38962000.0", "Short Term Debt Issuance": "37098000.0", "Net Long Term Debt Issuance": "-1288000.0", "Long Term Debt Payments": "-1288000.0", "Long Term Debt Issuance": "0.0", "Investing Cash Flow": "-9100000.0", "Cash Flow From Continuing Investing Activities": "-9100000.0", "Net PPE Purchase And Sale": "-9100000.0", "Sale Of PPE": "0.0", "Purchase Of PPE": "-9100000.0", "Operating Cash Flow": "34842000.0", "Cash Flow From Continuing Operating Activities": "34842000.0", "Change In Working Capital": "-3812000.0", "Change In Other Working Capital": "-980000.0", "Change In Payables And Accrued Expense": "-1365000.0", "Change In Accrued Expense": "3551000.0", "Change In Payable": "-4916000.0", "Change In Account Payable": "-4916000.0", "Change In Prepaid Assets": "-5825000.0", "Change In Inventory": "1808000.0", "Change In Receivables": "2550000.0", "Changes In Account Receivables": "2550000.0", "Stock Based Compensation": "2923000.0", "Asset Impairment Charge": "nan", "Deferred Tax": "2473000.0", "Deferred Income Tax": "2473000.0", "Depreciation Amortization Depletion": "12912000.0", "Depreciation And Amortization": "12912000.0", "Operating Gains Losses": "22000.0", "Net Foreign Currency Exchange Gain Loss": "-58000.0", "Net Income From Continuing Operations": "20324000.0"}, "2022": {"Free Cash Flow": "2394000.0", "Repurchase Of Capital Stock": "-482000.0", "Repayment Of Debt": "-193645000.0", "Issuance Of Debt": "190172000.0", "Capital Expenditure": "-16588000.0", "Interest Paid Supplemental Data": "1677000.0", "Income Tax Paid Supplemental Data": "6649000.0", "End Cash Position": "4183000.0", "Beginning Cash Position": "6146000.0", "Changes In Cash": "-1963000.0", "Financing Cash Flow": "-4357000.0", "Cash Flow From Continuing Financing Activities": "-4357000.0", "Net Other Financing Charges": "-884000.0", "Net Common Stock Issuance": "-482000.0", "Common Stock Payments": "-482000.0", "Net Issuance Payments Of Debt": "-3473000.0", "Net Short Term Debt Issuance": "-2560000.0", "Short Term Debt Payments": "-167732000.0", "Short Term Debt Issuance": "165172000.0", "Net Long Term Debt Issuance": "-913000.0", "Long Term Debt Payments": "-25913000.0", "Long Term Debt Issuance": "25000000.0", "Investing Cash Flow": "-16588000.0", "Cash Flow From Continuing Investing Activities": "-16588000.0", "Net PPE Purchase And Sale": "-16588000.0", "Sale Of PPE": "0.0", "Purchase Of PPE": "-16588000.0", "Operating Cash Flow": "18982000.0", "Cash Flow From Continuing Operating Activities": "18982000.0", "Change In Working Capital": "-5595000.0", "Change In Other Working Capital": "-713000.0", "Change In Payables And Accrued Expense": "1932000.0", "Change In Accrued Expense": "-4067000.0", "Change In Payable": "5999000.0", "Change In Account Payable": "5999000.0", "Change In Prepaid Assets": "928000.0", "Change In Inventory": "1258000.0", "Change In Receivables": "-9000000.0", "Changes In Account Receivables": "-9000000.0", "Stock Based Compensation": "2329000.0", "Asset Impairment Charge": "nan", "Deferred Tax": "-3469000.0", "Deferred Income Tax": "-3469000.0", "Depreciation Amortization Depletion": "11884000.0", "Depreciation And Amortization": "11884000.0", "Operating Gains Losses": "1630000.0", "Net Foreign Currency Exchange Gain Loss": "396000.0", "Net Income From Continuing Operations": "12203000.0"}, "2021": {"Free Cash Flow": "977000.0", "Repurchase Of Capital Stock": "-96000.0", "Repayment Of Debt": "-48628000.0", "Issuance Of Debt": "49610000.0", "Capital Expenditure": "-11569000.0", "Interest Paid Supplemental Data": "1840000.0", "Income Tax Paid Supplemental Data": "5067000.0", "End Cash Position": "6146000.0", "Beginning Cash Position": "4131000.0", "Changes In Cash": "2015000.0", "Financing Cash Flow": "884000.0", "Cash Flow From Continuing Financing Activities": "884000.0", "Net Other Financing Charges": "-98000.0", "Net Common Stock Issuance": "-96000.0", "Common Stock Payments": "-96000.0", "Net Issuance Payments Of Debt": "982000.0", "Net Short Term Debt Issuance": "4004000.0", "Short Term Debt Payments": "-45606000.0", "Short Term Debt Issuance": "49610000.0", "Net Long Term Debt Issuance": "-3022000.0", "Long Term Debt Payments": "-3022000.0", "Long Term Debt Issuance": "0.0", "Investing Cash Flow": "-11415000.0", "Cash Flow From Continuing Investing Activities": "-11415000.0", "Net PPE Purchase And Sale": "-11415000.0", "Sale Of PPE": "154000.0", "Purchase Of PPE": "-11569000.0", "Operating Cash Flow": "12546000.0", "Cash Flow From Continuing Operating Activities": "12546000.0", "Change In Working Capital": "-5895000.0", "Change In Other Working Capital": "-436000.0", "Change In Payables And Accrued Expense": "10827000.0", "Change In Accrued Expense": "5481000.0", "Change In Payable": "5346000.0", "Change In Account Payable": "5346000.0", "Change In Prepaid Assets": "-565000.0", "Change In Inventory": "-6769000.0", "Change In Receivables": "-8952000.0", "Changes In Account Receivables": "-8952000.0", "Stock Based Compensation": "1886000.0", "Asset Impairment Charge": "0.0", "Deferred Tax": "-475000.0", "Deferred Income Tax": "-475000.0", "Depreciation Amortization Depletion": "11616000.0", "Depreciation And Amortization": "11616000.0", "Operating Gains Losses": "743000.0", "Net Foreign Currency Exchange Gain Loss": "172000.0", "Net Income From Continuing Operations": "4671000.0"}, "2020": {"Free Cash Flow": "24481000.0", "Repurchase Of Capital Stock": "-20000.0", "Repayment Of Debt": "-107106000.0", "Issuance Of Debt": "86958000.0", "Capital Expenditure": "-3683000.0", "Interest Paid Supplemental Data": "3854000.0", "Income Tax Paid Supplemental Data": "570000.0", "End Cash Position": "4131000.0", "Beginning Cash Position": "1856000.0", "Changes In Cash": "2275000.0", "Financing Cash Flow": "-22206000.0", "Cash Flow From Continuing Financing Activities": "-22206000.0", "Net Other Financing Charges": "-2038000.0", "Net Common Stock Issuance": "-20000.0", "Common Stock Payments": "-20000.0", "Net Issuance Payments Of Debt": "-20148000.0", "Net Short Term Debt Issuance": "-11588000.0", "Short Term Debt Payments": "-68381000.0", "Short Term Debt Issuance": "56793000.0", "Net Long Term Debt Issuance": "-8560000.0", "Long Term Debt Payments": "-38725000.0", "Long Term Debt Issuance": "30165000.0", "Investing Cash Flow": "-3683000.0", "Cash Flow From Continuing Investing Activities": "-3683000.0", "Net PPE Purchase And Sale": "-3683000.0", "Sale Of PPE": "0.0", "Purchase Of PPE": "-3683000.0", "Operating Cash Flow": "28164000.0", "Cash Flow From Continuing Operating Activities": "28164000.0", "Change In Working Capital": "5648000.0", "Change In Other Working Capital": "-264000.0", "Change In Payables And Accrued Expense": "-232000.0", "Change In Accrued Expense": "2910000.0", "Change In Payable": "-3142000.0", "Change In Account Payable": "-3142000.0", "Change In Prepaid Assets": "-2018000.0", "Change In Inventory": "3322000.0", "Change In Receivables": "4840000.0", "Changes In Account Receivables": "4840000.0", "Stock Based Compensation": "1355000.0", "Asset Impairment Charge": "nan", "Deferred Tax": "1097000.0", "Deferred Income Tax": "1097000.0", "Depreciation Amortization Depletion": "11662000.0", "Depreciation And Amortization": "11662000.0", "Operating Gains Losses": "237000.0", "Net Foreign Currency Exchange Gain Loss": "237000.0", "Net Income From Continuing Operations": "8165000.0"}}